adsb_exchange_python/__init__.py
adsb_exchange_python/adsb_exchange_python.py
adsb_exchange_python-1.0.0.dist-info/LICENSE
adsb_exchange_python-1.0.0.dist-info/METADATA
adsb_exchange_python-1.0.0.dist-info/WHEEL
adsb_exchange_python-1.0.0.dist-info/top_level.txt
adsb_exchange_python-1.0.0.dist-info/RECORD
