Metadata-Version: 2.1
Name: adsb-exchange-python
Version: 1.0.0
Summary: A minimal wrapper for the basic ADS-B Exchange API
Author-email: Nafeeur Rahman <nafeeur@mit.edu>
License: GNU GENERAL PUBLIC LICENSE
Project-URL: Source, https://github.com/nafeeur/adsb_exchange_python
Project-URL: Tracker, https://github.com/nafeeur/adsb_exchange_python/issues
Keywords: adsb,aviation,api,wrapper,ads-b,ads-b exchange
Classifier: Programming Language :: Python :: 3
Classifier: Programming Language :: Python :: 3.6
Classifier: Programming Language :: Python :: 3.7
Classifier: Programming Language :: Python :: 3.8
Classifier: Programming Language :: Python :: 3.9
Classifier: Programming Language :: Python :: 3.10
Classifier: License :: OSI Approved :: GNU General Public License v3 (GPLv3)
Classifier: Operating System :: OS Independent
Requires-Python: >=3.6
License-File: LICENSE
Requires-Dist: requests >=2.20.0
Requires-Dist: urllib3 >=1.25.0
